ordered_argparse/__init__.py
ordered_argparse/ordered_argparse.py
ordered_argparse-1.0.10.dist-info/LICENSE
ordered_argparse-1.0.10.dist-info/METADATA
ordered_argparse-1.0.10.dist-info/WHEEL
ordered_argparse-1.0.10.dist-info/entry_points.txt
ordered_argparse-1.0.10.dist-info/top_level.txt
ordered_argparse-1.0.10.dist-info/RECORD
