Metadata-Version: 2.1
Name: ordered-argparse
Version: 1.0.10
Summary: Modified version of argparse which remembers the order of CLI arguments
Home-page: https://github.com/Nagidal/ordered_argparse
Author: Sven Siegmund
Author-email: sven.siegmund@gmail.com
License: UNKNOWN
Keywords: cli argument parsing
Platform: any
Classifier: Development Status :: 5 - Production/Stable
Classifier: Intended Audience :: End Users/Desktop
Classifier: Intended Audience :: Developers
Classifier: Intended Audience :: System Administrators
Classifier: Environment :: Console
Classifier: Topic :: Software Development
Classifier: Topic :: Utilities
Classifier: License :: OSI Approved :: MIT License
Classifier: Natural Language :: English
Classifier: Programming Language :: Python :: 3.9
Classifier: Operating System :: OS Independent
Classifier: Operating System :: Microsoft :: Windows
Classifier: Operating System :: POSIX :: Linux
Classifier: Operating System :: MacOS :: MacOS X
Requires-Python: >=3.9
